Workbook

Sheet Raw_Data
A1: Statement | B1: Metric | C1: FY2022 | D1: FY2023 | E1: FY2024 | F1: FY2025 | G1: FY2026
A3: Income Statement | B3: Revenue | C3: 198270 | D3: 211915 | E3: 245122 | F3: 281724 | G3: 331839
A4: Income Statement | B4: Cost of Revenue | C4: 62650 | D4: 65863 | E4: 74114 | F4: 87831 | G4: 106374
A5: Income Statement | B5: Gross Profit | C5: 135620 | D5: 146052 | E5: 171008 | F5: 193893 | G5: 225465
A6: Income Statement | B6: Research & Development | C6: 24512 | D6: 27195 | E6: 29510 | F6: 32488 | G6: 35562
A7: Income Statement | B7: Sales & Marketing | C7: 21825 | D7: 22759 | E7: 24456 | F7: 25654 | G7: 26710
A8: Income Statement | B8: General & Administrative | C8: 5900 | D8: 7575 | E8: 7609 | F8: 7223 | G8: 7956
A9: Income Statement | B9: Operating Income | C9: 83383 | D9: 88523 | E9: 109433 | F9: 128528 | G9: 155237
A10: Income Statement | B10: Other Income/(Expense), Net | C10: 333 | D10: 788 | E10: -1646 | F10: -4901 | G10: 10697
A11: Income Statement | B11: Income Before Tax | C11: 83716 | D11: 89311 | E11: 107787 | F11: 123627 | G11: 165934
A12: Income Statement | B12: Income Tax | C12: 10978 | D12: 16950 | E12: 19651 | F12: 21795 | G12: 32185
A13: Income Statement | B13: Net Income | C13: 72738 | D13: 72361 | E13: 88136 | F13: 101832 | G13: 133749
A14: Balance Sheet | B14: Cash & Cash Equivalents | C14: 13931 | D14: 34704 | E14: 18315 | F14: 30242 | G14: 20935
... A80: Cash Flow | B80: Ending Cash | C80: 13931 | D80: 34704 | E80: 18315 | F80: 30242 | G80: 20935

Sheet Income_Statement
A1: Income Statement ($m) | B1: FY2022 | C1: FY2023 | D1: FY2024 | E1: FY2025 | F1: FY2026
A3: Revenue | B3: 198270 | C3: 211915 | D3: 245122 | E3: 281724 | F3: 331839
A4: Cost of Revenue | B4: 62650 | C4: 65863 | D4: 74114 | E4: 87831 | F4: 106374
A5: Gross Profit | B5: 135620 | C5: 146052 | D5: 171008 | E5: 193893 | F5: 225465
A6: R&D | B6: 24512 | C6: 27195 | D6: 29510 | E6: 32488 | F6: 35562
A7: Sales & Marketing | B7: 21825 | C7: 22759 | D7: 24456 | E7: 25654 | F7: 26710
A8: G&A | B8: 5900 | C8: 7575 | D8: 7609 | E8: 7223 | F8: 7956
A9: Operating Income | B9: 83383 | C9: 88523 | D9: 109433 | E9: 128528 | F9: 155237
A10: Other Income, Net | B10: 333 | C10: 788 | D10: -1646 | E10: -4901 | F10: 10697
A11: Income Before Tax | B11: 83716 | C11: 89311 | D11: 107787 | E11: 123627 | F11: 165934
A12: Income Tax | B12: 10978 | C12: 16950 | D12: 19651 | E12: 21795 | F12: 32185
A13: Net Income (Profit) | B13: 72738 | C13: 72361 | D13: 88136 | E13: 101832 | F13: 133749

Sheet Balance_Sheet
A1: Balance Sheet ($ millions) | B1: FY2022 | C1: FY2023 | D1: FY2024 | E1: FY2025 | F1: FY2026
A2: ASSETS
A3: Cash & Cash Equivalents | B3: 13931 | C3: 34704 | D3: 18315 | E3: 30242 | F3: 20935
A4: Short-Term Investments | B4: 90826 | C4: 76558 | D4: 57228 | E4: 64323 | F4: 55908
A5: Accounts Receivable | B5: 44261 | C5: 48688 | D5: 56924 | E5: 69905 | F5: 80876
A6: Inventory | B6: 3742 | C6: 2500 | D6: 1246 | E6: 938 | F6: 1397
A7: Other Current Assets | B7: 16924 | C7: 21807 | D7: 26021 | E7: 25723 | F7: 48594
A8: Total Current Assets | B8: 169684 | C8: 184257 | D8: 159734 | E8: 191131 | F8: 207710
A9: PP&E, Net | B9: 74398 | C9: 95641 | D9: 135591 | E9: 204966 | F9: 313076
A10: Operating Lease ROU Assets | B10: 13148 | C10: 14346 | D10: 18961 | E10: 24823 | F10: 24177
A11: Equity & Other Investments | B11: 6891 | C11: 9879 | D11: 14600 | E11: 15405 | F11: 36348
A12: Goodwill | B12: 67524 | C12: 67886 | D12: 119220 | E12: 119509 | F12: 119651
A13: Intangible Assets, Net | B13: 11298 | C13: 9366 | D13: 27597 | E13: 22604 | F13: 18609
A14: Other Long-Term Assets | B14: 21897 | C14: 30601 | D14: 36460 | E14: 40565 | F14: 38805
A15: Total Assets | B15: 364840 | C15: 411976 | D15: 512163 | E15: 619003 | F15: 758376
A16: LIABILITIES
A17: Accounts Payable | B17: 19000 | C17: 18095 | D17: 21996 | E17: 27724 | F17: 42416
A18: Short-Term Debt | B18: 0 | C18: 0 | D18: 6693 | E18: 0 | F18: 0
A19: Current Portion of Long-Term Debt | B19: 2749 | C19: 5247 | D19: 2249 | E19: 2999 | F19: 9227
A20: Accrued Compensation | B20: 10661 | C20: 11009 | D20: 12564 | E20: 13709 | F20: 14945
A21: Short-Term Income Taxes | B21: 4067 | C21: 4152 | D21: 5017 | E21: 7211 | F21: 2534
A22: Short-Term Unearned Revenue | B22: 45538 | C22: 50901 | D22: 57582 | E22: 64555 | F22: 72965
A23: Other Current Liabilities | B23: 13067 | C23: 14745 | D23: 19185 | E23: 25020 | F23: 26738
A24: Total Current Liabilities | B24: 95082 | C24: 104149 | D24: 125286 | E24: 141218 | F24: 168825
A25: Long-Term Debt | B25: 47032 | C25: 41990 | D25: 42688 | E25: 40152 | F25: 31067
A26: Long-Term Income Taxes | B26: 26069 | C26: 25560 | D26: 27931 | E26: 25986 | F26: 28647
A27: Long-Term Unearned Revenue | B27: 2870 | C27: 2912 | D27: 2602 | E27: 2710 | F27: 2747
A28: Deferred Income Taxes | B28: 230 | C28: 433 | D28: 2618 | E28: 2835 | F28: 3054
... A31: Total Liabilities | B31: 198298 | C31: 205753 | D31: 243686 | E31: 275524 | F31: 315989
A32: STOCKHOLDERS' EQUITY
A33: Common Stock & Paid-In Capital | B33: 86939 | C33: 93718 | D33: 100923 | E33: 109095 | F33: 117406
A34: Retained Earnings | B34: 84281 | C34: 118848 | D34: 173144 | E34: 237731 | F34: 328265
A35: Accumulated Other Comprehensive Loss | B35: -4678 | C35: -6343 | D35: -5590 | E35: -3347 | F35: -3284
A36: Total Stockholders' Equity | B36: 166542 | C36: 206223 | D36: 268477 | E36: 343479 | F36: 442387
A37: Total Liabilities + Equity | B37: 364840 | C37: 411976 | D37: 512163 | E37: 619003 | F37: 758376

Sheet Cash_Flow
A1: Cash Flow Statement ($m) | B1: FY2022 | C1: FY2023 | D1: FY2024 | E1: FY2025 | F1: FY2026
A2: OPERATING ACTIVITIES
A3: Net Income | B3: 72738 | C3: 72361 | D3: 88136 | E3: 101832 | F3: 133749
A4: D&A and Other | B4: 14460 | C4: 13861 | D4: 22287 | E4: 29433 | F4: 38534
A5: Stock-Based Compensation | B5: 7502 | C5: 9611 | D5: 10734 | E5: 11974 | F5: 12405
A6: Investment/Derivative Gains (Losses) | B6: -409 | C6: 196 | D6: 305 | E6: 5329 | F6: -11047
A7: Deferred Income Taxes | B7: -5702 | C7: -6059 | D7: -4738 | E7: -7056 | F7: 14189
A8: Change in Accounts Receivable | B8: -6834 | C8: -4087 | D8: -7191 | E8: -10581 | F8: -12737
A9: Change in Inventory | B9: -1123 | C9: 1242 | D9: 1284 | E9: 309 | F9: -461
A10: Change in Other Current Assets | B10: -709 | C10: -1991 | D10: -1648 | E10: -3044 | F10: -2627
A11: Change in Other Long-Term Assets | B11: -2805 | C11: -2833 | D11: -6817 | E11: -2950 | F11: -3964
A12: Change in Accounts Payable | B12: 2943 | C12: -2721 | D12: 3545 | E12: 569 | F12: 5268
A13: Change in Unearned Revenue | B13: 5109 | C13: 5535 | D13: 5348 | E13: 5438 | F13: 9361
A14: Change in Income Taxes | B14: 696 | C14: -358 | D14: 1687 | E14: -38 | F14: -1875
... A17: Cash Flow from Operations (CFO) | B17: 89035 | C17: 87582 | D17: 118548 | E17: 136162 | F17: 182935
A18: INVESTING ACTIVITIES
A19: Additions to PP&E / CapEx | B19: -23886 | C19: -28107 | D19: -44477 | E19: -64551 | F19: -115948
A20: Acquisitions | B20: -22038 | C20: -1670 | D20: -69132 | E20: -5978 | F20: -1743
A21: Purchases of Investments | B21: -26456 | C21: -37651 | D21: -17732 | E21: -29775 | F21: -58351
A22: Maturities of Investments | B22: 16451 | C22: 33510 | D22: 24775 | E22: 16079 | F22: 34605
A23: Sales of Investments | B23: 28443 | C23: 14354 | D23: 10894 | E23: 9309 | F23: 21798
A24: Other Investing, Net | B24: -2825 | C24: -3116 | D24: -1298 | E24: 2317 | F24: -19861
A25: Cash Flow from Investing (CFI) | B25: -30311 | C25: -22680 | D25: -96970 | E25: -72599 | F25: -139500
A26: FINANCING ACTIVITIES
A27: Short-Term Debt Issuance/(Repayment), Net | B27: 0 | C27: 0 | D27: 5250 | E27: -5746 | F27: 0
A28: Debt Issued | B28: 0 | C28: 0 | D28: 24395 | E28: 0 | F28: 0
A29: Debt Repayment | B29: -9023 | C29: -2750 | D29: -29070 | E29: -3216 | F29: -3000
A30: Common Stock Issued | B30: 1841 | C30: 1866 | D30: 2002 | E30: 2056 | F30: 2009
A31: Share Repurchases | B31: -32696 | C31: -22245 | D31: -17254 | E31: -18420 | F31: -22271
A32: Dividends Paid | B32: -18135 | C32: -19800 | D32: -21771 | E32: -24082 | F32: -26445
A33: Other Financing, Net | B33: -863 | C33: -1006 | D33: -1309 | E33: -2291 | F33: -2839
A34: Cash Flow from Financing (CFF) | B34: -58876 | C34: -43935 | D34: -37757 | E34: -51699 | F34: -52546
A35: FX Effect on Cash | B35: -141 | C35: -194 | D35: -210 | E35: 63 | F35: -196
A36: Net Change in Cash | B36: -293 | C36: 20773 | D36: -16389 | E36: 11927 | F36: -9307
A37: Beginning Cash | B37: 14224 | C37: 13931 | D37: 34704 | E37: 18315 | F37: 30242
A38: Ending Cash | B38: 13931 | C38: 34704 | D38: 18315 | E38: 30242 | F38: 20935

Sheet Analysis
A1: Metric | B1: FY2022 | C1: FY2023 | D1: FY2024 | E1: FY2025 | F1: FY2026
A3: Revenue Growth | B3: N/A | C3: =((Income_Statement!C3-Income_Statement!B3)/Income_Statement!B3)*100 -> 6.8820296 | D3: =((Income_Statement!D3-Income_Statement!C3)/Income_Statement!C3)*100 -> 15.669962 | E3: =((Income_Statement!E3-Income_Statement!D3)/Income_Statement!D3)*100 -> 14.932156 | F3: =((Income_Statement!F3-Income_Statement!E3)/Income_Statement!E3)*100 -> 17.788687
A4: Net Income Growth | B4: N/A | C4: =((Income_Statement!C13 - Income_Statement!B13) / Income_Statement!B13) * 100 -> -0.51829855 | D4: =((Income_Statement!D13 - Income_Statement!C13) / Income_Statement!C13) * 100 -> 21.800417 | E4: =((Income_Statement!E13 - Income_Statement!D13) / Income_Statement!D13) * 100 -> 15.539621 | F4: =((Income_Statement!F13 - Income_Statement!E13) / Income_Statement!E13) * 100 -> 31.3428
A5: Gross Margin | B5: =(Income_Statement!B5/Income_Statement!B3) * 100 -> 68.401674 | C5: =(Income_Statement!C5/Income_Statement!C3) * 100 -> 68.920086 | D5: =(Income_Statement!D5/Income_Statement!D3) * 100 -> 69.764444 | E5: =(Income_Statement!E5/Income_Statement!E3) * 100 -> 68.823742 | F5: =(Income_Statement!F5/Income_Statement!F3) * 100 -> 67.944093
A6: EBIT Margin | B6: =(Income_Statement!B9/Income_Statement!B3) * 100 -> 42.055278 | C6: =(Income_Statement!C9/Income_Statement!C3) * 100 -> 41.772881 | D6: =(Income_Statement!D9/Income_Statement!D3) * 100 -> 44.6443 | E6: =(Income_Statement!E9/Income_Statement!E3) * 100 -> 45.621956 | F6: =(Income_Statement!F9/Income_Statement!F3) * 100 -> 46.780818
A7: EBITDA Proxy | B7: =Income_Statement!B9 + Cash_Flow!B4 -> 97843 | C7: =Income_Statement!C9 + Cash_Flow!C4 -> 102384 | D7: =Income_Statement!D9 + Cash_Flow!D4 -> 131720 | E7: =Income_Statement!E9 + Cash_Flow!E4 -> 157961 | F7: =Income_Statement!F9 + Cash_Flow!F4 -> 193771
A8: EBITDA Proxy Margin | B8: =(B7/Income_Statement!B3) * 100 -> 49.348363 | C8: =(C7/Income_Statement!C3) * 100 -> 48.313711 | D8: =(D7/Income_Statement!D3) * 100 -> 53.736507 | E8: =(E7/Income_Statement!E3) * 100 -> 56.069415 | F8: =(F7/Income_Statement!F3) * 100 -> 58.393076
A9: Current Ratio | B9: =Balance_Sheet!B8 / Balance_Sheet!B24 -> 1.784607 | C9: =Balance_Sheet!C8 / Balance_Sheet!C24 -> 1.7691673 | D9: =Balance_Sheet!D8 / Balance_Sheet!D24 -> 1.2749549 | E9: =Balance_Sheet!E8 / Balance_Sheet!E24 -> 1.3534464 | F9: =Balance_Sheet!F8 / Balance_Sheet!F24 -> 1.2303273
A10: Quick Ratio | B10: =(Balance_Sheet!B8-Balance_Sheet!B6)/ Balance_Sheet!B24 -> 1.7452515 | C10: =(Balance_Sheet!C8-Balance_Sheet!C6)/ Balance_Sheet!C24 -> 1.7451632 | D10: =(Balance_Sheet!D8-Balance_Sheet!D6)/ Balance_Sheet!D24 -> 1.2650097 | E10: =(Balance_Sheet!E8-Balance_Sheet!E6)/ Balance_Sheet!E24 -> 1.3468042 | F10: =(Balance_Sheet!F8-Balance_Sheet!F6)/ Balance_Sheet!F24 -> 1.2220524
A11: Total Debt | B11: =Balance_Sheet!B18 +Balance_Sheet!B25+Balance_Sheet!B19 -> 49781 | C11: =Balance_Sheet!C18 +Balance_Sheet!C25+Balance_Sheet!C19 -> 47237 | D11: =Balance_Sheet!D18 +Balance_Sheet!D25+Balance_Sheet!D19 -> 51630 | E11: =Balance_Sheet!E18 +Balance_Sheet!E25+Balance_Sheet!E19 -> 43151 | F11: =Balance_Sheet!F18 +Balance_Sheet!F25+Balance_Sheet!F19 -> 40294
A12: Debt / Equity | B12: =B11/Balance_Sheet!B36 -> 0.29890958 | C12: =C11/Balance_Sheet!C36 -> 0.22905786 | D12: =D11/Balance_Sheet!D36 -> 0.19230698 | E12: =E11/Balance_Sheet!E36 -> 0.12562922 | F12: =F11/Balance_Sheet!F36 -> 0.091083147
A13: Debt / EBITDA Proxy | B13: =B11/B7 -> 0.50878448 | C13: =C11/C7 -> 0.46137092 | D13: =D11/D7 -> 0.39196781 | E13: =E11/E7 -> 0.27317502 | F13: =F11/F7 -> 0.20794649
A14: Net Debt | B14: =B11 - Balance_Sheet!B3 -> 35850 | C14: =C11 - Balance_Sheet!C3 -> 12533 | D14: =D11 - Balance_Sheet!D3 -> 33315 | E14: =E11 - Balance_Sheet!E3 -> 12909 | F14: =F11 - Balance_Sheet!F3 -> 19359
A15: Net Debt / EBITDA Proxy | B15: =B14/B7 -> 0.36640332 | C15: =C14/C7 -> 0.1224117 | D15: =D14/D7 -> 0.25292287 | E15: =E14/E7 -> 0.081722704 | F15: =F14/F7 -> 0.099906591
A16: Operating Working Capital | B16: =Balance_Sheet!B5+Balance_Sheet!B6 - Balance_Sheet!B17 -> 29003 | C16: =Balance_Sheet!C5+Balance_Sheet!C6 - Balance_Sheet!C17 -> 33093 | D16: =Balance_Sheet!D5+Balance_Sheet!D6 - Balance_Sheet!D17 -> 36174 | E16: =Balance_Sheet!E5+Balance_Sheet!E6 - Balance_Sheet!E17 -> 43119 | F16: =Balance_Sheet!F5+Balance_Sheet!F6 - Balance_Sheet!F17 -> 39857
A17: AR Growth | B17: N/A | C17: =((Balance_Sheet!C5 - Balance_Sheet!B5)/Balance_Sheet!B5)* 100 -> 10.002033 | D17: =((Balance_Sheet!D5 - Balance_Sheet!C5)/Balance_Sheet!C5)* 100 -> 16.915872 | E17: =((Balance_Sheet!E5 - Balance_Sheet!D5)/Balance_Sheet!D5)* 100 -> 22.80409 | F17: =((Balance_Sheet!F5 - Balance_Sheet!E5)/Balance_Sheet!E5)* 100 -> 15.694156
A18: Inventory Growth | B18: N/A | C18: =((Balance_Sheet!C6 - Balance_Sheet!B6)/Balance_Sheet!B6) * 100 -> -33.190807 | D18: =((Balance_Sheet!D6 - Balance_Sheet!C6)/Balance_Sheet!C6) * 100 -> -50.16 | E18: =((Balance_Sheet!E6 - Balance_Sheet!D6)/Balance_Sheet!D6) * 100 -> -24.719101 | F18: =((Balance_Sheet!F6 - Balance_Sheet!E6)/Balance_Sheet!E6) * 100 -> 48.933902
A19: AP Growth | B19: N/A | C19: =((Balance_Sheet!C17 - Balance_Sheet!B17) / Balance_Sheet!B17) * 100 -> -4.7631579 | D19: =((Balance_Sheet!D17 - Balance_Sheet!C17) / Balance_Sheet!C17) * 100 -> 21.558442 | E19: =((Balance_Sheet!E17 - Balance_Sheet!D17) / Balance_Sheet!D17) * 100 -> 26.041098 | F19: =((Balance_Sheet!F17 - Balance_Sheet!E17) / Balance_Sheet!E17) * 100 -> 52.993796
A20: FCF | B20: =Cash_Flow!B17 + Cash_Flow!B19 -> 65149 | C20: =Cash_Flow!C17 + Cash_Flow!C19 -> 59475 | D20: =Cash_Flow!D17 + Cash_Flow!D19 -> 74071 | E20: =Cash_Flow!E17 + Cash_Flow!E19 -> 71611 | F20: =Cash_Flow!F17 + Cash_Flow!F19 -> 66987
A21: FCF Margin | B21: =(B20/Income_Statement!B3) * 100 -> 32.858728 | C21: =(C20/Income_Statement!C3) * 100 -> 28.065498 | D21: =(D20/Income_Statement!D3) * 100 -> 30.218014 | E21: =(E20/Income_Statement!E3) * 100 -> 25.41885 | F21: =(F20/Income_Statement!F3) * 100 -> 20.186597
A22: FCF Conversion | B22: =(B20/Income_Statement!B13) * 100 -> 89.566664 | C22: =(C20/Income_Statement!C13) * 100 -> 82.192065 | D22: =(D20/Income_Statement!D13) * 100 -> 84.041708 | E22: =(E20/Income_Statement!E13) * 100 -> 70.322688 | F22: =(F20/Income_Statement!F13) * 100 -> 50.084113
A23: CapEx / Revenue | B23: =(Cash_Flow!B19/Income_Statement!B3) * 100*(-1) -> 12.047208 | C23: =(Cash_Flow!C19/Income_Statement!C3) * 100*(-1) -> 13.263337 | D23: =(Cash_Flow!D19/Income_Statement!D3) * 100*(-1) -> 18.144842 | E23: =(Cash_Flow!E19/Income_Statement!E3) * 100*(-1) -> 22.912851 | F23: =(Cash_Flow!F19/Income_Statement!F3) * 100*(-1) -> 34.941041

Sheet Findings
A1: Finding | B1: Metric | C1: Current | D1: Previous / Comparator | E1: Change | F1: Severity | G1: Investigation
A3: Revenue growth | B3: Revenue Growth | C3: =Analysis!F3 -> 17.788687 | D3: =Analysis!E3 -> 14.932156 | E3: =C3 - D3 -> 2.8565306 | F3: =IF(ABS(E3)>=10,"High",IF(ABS(E3)>=5,"Medium","Low")) -> Low | G3: Assess drivers of revenue growth and identify key segment contributions.
A4: Margin compression | B4: Gross Margin | C4: =Analysis!F5 -> 67.944093 | D4: =Analysis!E5 -> 68.823742 | E4: =C4 - D4 -> -0.87964902 | F4: =IF(ABS(E4)>=3,"High",IF(ABS(E4)>=1,"Medium","Low")) -> Low | G4: Investigate cost of revenue growth and drivers of gross margin pressure.
A5: Receivables growth | B5: AR Growth | C5: =Analysis!F17 -> 15.694156 | D5: =Analysis!E17 -> 22.80409 | E5: =C5 - D5 -> -7.1099333 | F5: =IF(ABS(E5)>=15,"High",IF(ABS(E5)>=7.5,"Medium","Low")) -> Low | G5: Compare AR growth with revenue growth and assess potential collection risk.
A6: Cash conversion | B6: FCF Conversion | C6: =Analysis!F22 -> 50.084113 | D6: =Analysis!E22 -> 70.322688 | E6: =C6 - D6 -> -20.238576 | F6: =IF(ABS(E6)>=15,"High",IF(ABS(E6)>=7.5,"Medium","Low")) -> High | G6: Investigate rising CapEx and working capital movements contributing to weaker FCF conversion.
A7: Leverage | B7: Debt/EBITDA Proxy | C7: =Analysis!F13 -> 0.20794649 | D7: =Analysis!E13 -> 0.27317502 | E7: =C7 - D7 -> -0.065228531 | F7: =IF(ABS(E7)>=1,"High",IF(ABS(E7)>=0.5,"Medium","Low")) -> Low | G7: Assess debt trend, repayment capacity, and leverage relative to operating performance.
A8: Earnings–Cash Flow Divergence | B8: Net Income Growth vs FCF Growth | C8: =Analysis!F4 -> 31.3428 | D8: =((Analysis!F20 - Analysis!E20) / Analysis!E20) * 100 -> -6.4571085 | E8: =C8 - D8 -> 37.799908 | F8: =IF(ABS(E8)>=20,"High",IF(ABS(E8)>=10,"Medium","Low")) -> High | G8: Investigate CapEx and working-capital movements driving divergence between earnings and free cash flow.
A9: Investment Intensity | B9: CapEx / Revenue | C9: =Analysis!F23 -> 34.941041 | D9: =Analysis!E23 -> 22.912851 | E9: =C9 - D9 -> 12.02819 | F9: =IF(ABS(E9)>=10,"High",IF(ABS(E9)>=5,"Medium","Low")) -> High | G9: Assess drivers of increased capital investment and implications for future cash generation and returns.
A10: Receivables vs Sales | B10: AR Growth vs Revenue Growth | C10: =Analysis!F17 -> 15.694156 | D10: =Analysis!F3 -> 17.788687 | E10: =C10 - D10 -> -2.0945304 | F10: =IF(E10>10,"High",IF(E10>5,"Medium","Low")) -> Low | G10: Monitor receivables growth relative to revenue and assess collection trends.

Sheet DCF

Sheet Company_Input
